mics-second/video/memo.v
// horizontal constants
`define H_PW      96 // sync
`define H_FP      16 // front porch
`define H_DISPW  640 // active video
`define H_BP      48 // back porch
`define H_POL      0 // negative polarity
// vertical constants
`define V_PW       2 // sync
`define V_FP      10 // front porch, fixed from 33
`define V_DISPW  480 // active video
`define V_BP      33 // back porch, fixed from 10
`define V_POL      0 // negative polarity

module VGAtiming(
		 input PCLK_I,
		 input RST_I,
		 output BLANK_O,
		 output HSYNC_O,
		 output VSYNC_O,
		 output [10:0] HCNT_O,
		 output [10:0] VCNT_O
		 );
   reg [10:0] HCnt;  // horizontal counter
   reg [10:0] VCnt;  // vertical counter
   reg hsync, vsync; // horizontal/vertical sync
   reg blank; // data enable
   
   always @(posedge PCLK_I) begin
      if (RST_I == 1) begin
	 HCnt <= `H_DISPW + `H_FP + `H_PW + `H_BP - 1; 
	 VCnt <= `V_DISPW + `V_FP + `V_PW + `V_BP - 1;
	 blank <= 0;
	 hsync <= 1;
	 vsync <= 1;
      end else begin
	 // pixel/line counters and video data enable
	 if (HCnt == `H_DISPW + `H_FP + `H_PW + `H_BP - 1) begin
	    HCnt <= 0;
	 end else begin
	    HCnt <= HCnt + 1;
	 end
	 VCnt  <= 0;
	 blank <= 1;
	 hsync <= 1;
	 vsync <= 1;
      end
   end

   assign HCNT_O = HCnt;
   assign VCNT_O = VCnt;
   assign HSYNC_O = `H_POL ? ~hsync:hsync;
   assign VSYNC_O = `V_POL ? ~vsync:vsync;
   assign BLANK_O = blank;
endmodule // VGAtiming

module clock2_25MHz(output reg clk_25MHz);
   initial clk_25MHz = 0;
   always  #20 clk_25MHz = ~clk_25MHz; // 1/(25x10^6)=40psec 
endmodule

module VGAtimingSim;
   wire clk_25MHz,blank,hsync,vsync;
   wire [10:0] hcnt,vcnt;
   reg 	reset;
   clock2_25MHz clock2_25MHz(clk_25MHz);
   VGAtiming VGAtiming(clk_25MHz,reset,blank,hsync,vsync,hcnt,vcnt);
   initial begin
      $dumpfile("VGAtiming.vcd");
      $dumpvars(0,VGAtimingSim);
      $display("clk reset hsync vsync blank hcnt vcnt   time(ns)");
      $monitor(" %b    %b     %b     %b     %b   %3d  %3d",clk_25MHz,reset,hsync,vsync,blank,hcnt,vcnt,$stime);
      reset = 0;
      @(posedge clk_25MHz) reset = 1;
      @(posedge clk_25MHz) reset = 0;
      #30000;
      $finish;
   end
endmodule // VGAtimingSim

mics-second/video/VGAtiming.vcd
$date
	Mon Dec  2 15:01:53 2024
$end
$version
	Icarus Verilog
$end
$timescale
	1s
$end
$scope module VGAtimingSim $end
$var wire 1 ! vsync $end
$var wire 11 " vcnt [10:0] $end
$var wire 1 # hsync $end
$var wire 11 $ hcnt [10:0] $end
$var wire 1 % clk_25MHz $end
$var wire 1 & blank $end
$var reg 1 ' reset $end
$scope module VGAtiming $end
$var wire 1 & BLANK_O $end
$var wire 11 ( HCNT_O [10:0] $end
$var wire 1 # HSYNC_O $end
$var wire 1 ' RST_I $end
$var wire 11 ) VCNT_O [10:0] $end
$var wire 1 ! VSYNC_O $end
$var wire 1 % PCLK_I $end
$var reg 11 * HCnt [10:0] $end
$var reg 11 + VCnt [10:0] $end
$var reg 1 , blank $end
$var reg 1 - hsync $end
$var reg 1 . vsync $end
$upscope $end
$scope module clock2_25MHz $end
$var reg 1 % clk_25MHz $end
$upscope $end
$upscope $end
$enddefinitions $end
#0
$dumpvars
x.
x-
x,
bx +
bx *
bx )
bx (
0'
x&
0%
bx $
x#
bx "
x!
$end
#20
1!
1.
1#
1-
0&
0,
b1110 "
b1110 )
b1110 +
b10011 $
b10011 (
b10011 *
1'
1%
#40
0%
#60
0'
1%
#80
0%
#100
b0 "
b0 )
b0 +
b0 $
b0 (
b0 *
1%
#120
0%
#140
1&
1,
b1 $
b1 (
b1 *
1%
#160
0%
#180
b10 $
b10 (
b10 *
1%
#200
0%
#220
b11 $
b11 (
b11 *
1%
#240
0%
#260
b100 $
b100 (
b100 *
1%
#280
0%
#300
b101 $
b101 (
b101 *
1%
#320
0%
#340
b110 $
b110 (
b110 *
1%
#360
0%
#380
b111 $
b111 (
b111 *
1%
#400
0%
#420
0&
0,
b1000 $
b1000 (
b1000 *
1%
#440
0%
#460
b1001 $
b1001 (
b1001 *
1%
#480
0%
#500
b1010 $
b1010 (
b1010 *
1%
#520
0%
#540
0#
0-
b1011 $
b1011 (
b1011 *
1%
#560
0%
#580
b1100 $
b1100 (
b1100 *
1%
#600
0%
#620
b1101 $
b1101 (
b1101 *
1%
#640
0%
#660
b1110 $
b1110 (
b1110 *
1%
#680
0%
#700
b1111 $
b1111 (
b1111 *
1%
#720
0%
#740
b10000 $
b10000 (
b10000 *
1%
#760
0%
#780
1#
1-
b10001 $
b10001 (
b10001 *
1%
#800
0%
#820
b10010 $
b10010 (
b10010 *
1%
#840
0%
#860
b10011 $
b10011 (
b10011 *
1%
#880
0%
#900
b1 "
b1 )
b1 +
b0 $
b0 (
b0 *
1%
#920
0%
#940
1&
1,
b1 $
b1 (
b1 *
1%
#960
0%
#980
b10 $
b10 (
b10 *
1%
#1000
0%
#1020
b11 $
b11 (
b11 *
1%
#1040
0%
#1060
b100 $
b100 (
b100 *
1%
#1080
0%
#1100
b101 $
b101 (
b101 *
1%
#1120
0%
#1140
b110 $
b110 (
b110 *
1%
#1160
0%
#1180
b111 $
b111 (
b111 *
1%
#1200
0%
#1220
0&
0,
b1000 $
b1000 (
b1000 *
1%
#1240
0%
#1260
b1001 $
b1001 (
b1001 *
1%
#1280
0%
#1300
b1010 $
b1010 (
b1010 *
1%
#1320
0%
#1340
0#
0-
b1011 $
b1011 (
b1011 *
1%
#1360
0%
#1380
b1100 $
b1100 (
b1100 *
1%
#1400
0%
#1420
b1101 $
b1101 (
b1101 *
1%
#1440
0%
#1460
b1110 $
b1110 (
b1110 *
1%
#1480
0%
#1500
b1111 $
b1111 (
b1111 *
1%
#1520
0%
#1540
b10000 $
b10000 (
b10000 *
1%
#1560
0%
#1580
1#
1-
b10001 $
b10001 (
b10001 *
1%
#1600
0%
#1620
b10010 $
b10010 (
b10010 *
1%
#1640
0%
#1660
b10011 $
b10011 (
b10011 *
1%
#1680
0%
#1700
b10 "
b10 )
b10 +
b0 $
b0 (
b0 *
1%
#1720
0%
#1740
1&
1,
b1 $
b1 (
b1 *
1%
#1760
0%
#1780
b10 $
b10 (
b10 *
1%
#1800
0%
#1820
b11 $
b11 (
b11 *
1%
#1840
0%
#1860
b100 $
b100 (
b100 *
1%
#1880
0%
#1900
b101 $
b101 (
b101 *
1%
#1920
0%
#1940
b110 $
b110 (
b110 *
1%
#1960
0%
#1980
b111 $
b111 (
b111 *
1%
#2000
0%
#2020
0&
0,
b1000 $
b1000 (
b1000 *
1%
#2040
0%
#2060
b1001 $
b1001 (
b1001 *
1%
#2080
0%
#2100
b1010 $
b1010 (
b1010 *
1%
#2120
0%
#2140
0#
0-
b1011 $
b1011 (
b1011 *
1%
#2160
0%
#2180
b1100 $
b1100 (
b1100 *
1%
#2200
0%
#2220
b1101 $
b1101 (
b1101 *
1%
#2240
0%
#2260
b1110 $
b1110 (
b1110 *
1%
#2280
0%
#2300
b1111 $
b1111 (
b1111 *
1%
#2320
0%
#2340
b10000 $
b10000 (
b10000 *
1%
#2360
0%
#2380
1#
1-
b10001 $
b10001 (
b10001 *
1%
#2400
0%
#2420
b10010 $
b10010 (
b10010 *
1%
#2440
0%
#2460
b10011 $
b10011 (
b10011 *
1%
#2480
0%
#2500
b11 "
b11 )
b11 +
b0 $
b0 (
b0 *
1%
#2520
0%
#2540
1&
1,
b1 $
b1 (
b1 *
1%
#2560
0%
#2580
b10 $
b10 (
b10 *
1%
#2600
0%
#2620
b11 $
b11 (
b11 *
1%
#2640
0%
#2660
b100 $
b100 (
b100 *
1%
#2680
0%
#2700
b101 $
b101 (
b101 *
1%
#2720
0%
#2740
b110 $
b110 (
b110 *
1%
#2760
0%
#2780
b111 $
b111 (
b111 *
1%
#2800
0%
#2820
0&
0,
b1000 $
b1000 (
b1000 *
1%
#2840
0%
#2860
b1001 $
b1001 (
b1001 *
1%
#2880
0%
#2900
b1010 $
b1010 (
b1010 *
1%
#2920
0%
#2940
0#
0-
b1011 $
b1011 (
b1011 *
1%
#2960
0%
#2980
b1100 $
b1100 (
b1100 *
1%
#3000
0%
#3020
b1101 $
b1101 (
b1101 *
1%
#3040
0%
#3060
b1110 $
b1110 (
b1110 *
1%
#3080
0%
#3100
b1111 $
b1111 (
b1111 *
1%
#3120
0%
#3140
b10000 $
b10000 (
b10000 *
1%
#3160
0%
#3180
1#
1-
b10001 $
b10001 (
b10001 *
1%
#3200
0%
#3220
b10010 $
b10010 (
b10010 *
1%
#3240
0%
#3260
b10011 $
b10011 (
b10011 *
1%
#3280
0%
#3300
b100 "
b100 )
b100 +
b0 $
b0 (
b0 *
1%
#3320
0%
#3340
1&
1,
b1 $
b1 (
b1 *
1%
#3360
0%
#3380
b10 $
b10 (
b10 *
1%
#3400
0%
#3420
b11 $
b11 (
b11 *
1%
#3440
0%
#3460
b100 $
b100 (
b100 *
1%
#3480
0%
#3500
b101 $
b101 (
b101 *
1%
#3520
0%
#3540
b110 $
b110 (
b110 *
1%
#3560
0%
#3580
b111 $
b111 (
b111 *
1%
#3600
0%
#3620
0&
0,
b1000 $
b1000 (
b1000 *
1%
#3640
0%
#3660
b1001 $
b1001 (
b1001 *
1%
#3680
0%
#3700
b1010 $
b1010 (
b1010 *
1%
#3720
0%
#3740
0#
0-
b1011 $
b1011 (
b1011 *
1%
#3760
0%
#3780
b1100 $
b1100 (
b1100 *
1%
#3800
0%
#3820
b1101 $
b1101 (
b1101 *
1%
#3840
0%
#3860
b1110 $
b1110 (
b1110 *
1%
#3880
0%
#3900
b1111 $
b1111 (
b1111 *
1%
#3920
0%
#3940
b10000 $
b10000 (
b10000 *
1%
#3960
0%
#3980
1#
1-
b10001 $
b10001 (
b10001 *
1%
#4000
0%
#4020
b10010 $
b10010 (
b10010 *
1%
#4040
0%
#4060
b10011 $
b10011 (
b10011 *
1%
#4080
0%
#4100
b101 "
b101 )
b101 +
b0 $
b0 (
b0 *
1%
#4120
0%
#4140
1&
1,
b1 $
b1 (
b1 *
1%
#4160
0%
#4180
b10 $
b10 (
b10 *
1%
#4200
0%
#4220
b11 $
b11 (
b11 *
1%
#4240
0%
#4260
b100 $
b100 (
b100 *
1%
#4280
0%
#4300
b101 $
b101 (
b101 *
1%
#4320
0%
#4340
b110 $
b110 (
b110 *
1%
#4360
0%
#4380
b111 $
b111 (
b111 *
1%
#4400
0%
#4420
0&
0,
b1000 $
b1000 (
b1000 *
1%
#4440
0%
#4460
b1001 $
b1001 (
b1001 *
1%
#4480
0%
#4500
b1010 $
b1010 (
b1010 *
1%
#4520
0%
#4540
0#
0-
b1011 $
b1011 (
b1011 *
1%
#4560
0%
#4580
b1100 $
b1100 (
b1100 *
1%
#4600
0%
#4620
b1101 $
b1101 (
b1101 *
1%
#4640
0%
#4660
b1110 $
b1110 (
b1110 *
1%
#4680
0%
#4700
b1111 $
b1111 (
b1111 *
1%
#4720
0%
#4740
b10000 $
b10000 (
b10000 *
1%
#4760
0%
#4780
1#
1-
b10001 $
b10001 (
b10001 *
1%
#4800
0%
#4820
b10010 $
b10010 (
b10010 *
1%
#4840
0%
#4860
b10011 $
b10011 (
b10011 *
1%
#4880
0%
#4900
b110 "
b110 )
b110 +
b0 $
b0 (
b0 *
1%
#4920
0%
#4940
b1 $
b1 (
b1 *
1%
#4960
0%
#4980
b10 $
b10 (
b10 *
1%
#5000
0%
#5020
b11 $
b11 (
b11 *
1%
#5040
0%
#5060
b100 $
b100 (
b100 *
1%
#5080
0%
#5100
b101 $
b101 (
b101 *
1%
#5120
0%
#5140
b110 $
b110 (
b110 *
1%
#5160
0%
#5180
b111 $
b111 (
b111 *
1%
#5200
0%
#5220
b1000 $
b1000 (
b1000 *
1%
#5240
0%
#5260
b1001 $
b1001 (
b1001 *
1%
#5280
0%
#5300
b1010 $
b1010 (
b1010 *
1%
#5320
0%
#5340
0#
0-
b1011 $
b1011 (
b1011 *
1%
#5360
0%
#5380
b1100 $
b1100 (
b1100 *
1%
#5400
0%
#5420
b1101 $
b1101 (
b1101 *
1%
#5440
0%
#5460
b1110 $
b1110 (
b1110 *
1%
#5480
0%
#5500
b1111 $
b1111 (
b1111 *
1%
#5520
0%
#5540
b10000 $
b10000 (
b10000 *
1%
#5560
0%
#5580
1#
1-
b10001 $
b10001 (
b10001 *
1%
#5600
0%
#5620
b10010 $
b10010 (
b10010 *
1%
#5640
0%
#5660
b10011 $
b10011 (
b10011 *
1%
#5680
0%
#5700
b111 "
b111 )
b111 +
b0 $
b0 (
b0 *
1%
#5720
0%
#5740
b1 $
b1 (
b1 *
1%
#5760
0%
#5780
b10 $
b10 (
b10 *
1%
#5800
0%
#5820
b11 $
b11 (
b11 *
1%
#5840
0%
#5860
b100 $
b100 (
b100 *
1%
#5880
0%
#5900
b101 $
b101 (
b101 *
1%
#5920
0%
#5940
b110 $
b110 (
b110 *
1%
#5960
0%
#5980
b111 $
b111 (
b111 *
1%
#6000
0%
#6020
b1000 $
b1000 (
b1000 *
1%
#6040
0%
#6060
b1001 $
b1001 (
b1001 *
1%
#6080
0%
#6100
b1010 $
b1010 (
b1010 *
1%
#6120
0%
#6140
0#
0-
b1011 $
b1011 (
b1011 *
1%
#6160
0%
#6180
b1100 $
b1100 (
b1100 *
1%
#6200
0%
#6220
b1101 $
b1101 (
b1101 *
1%
#6240
0%
#6260
b1110 $
b1110 (
b1110 *
1%
#6280
0%
#6300
b1111 $
b1111 (
b1111 *
1%
#6320
0%
#6340
b10000 $
b10000 (
b10000 *
1%
#6360
0%
#6380
1#
1-
b10001 $
b10001 (
b10001 *
1%
#6400
0%
#6420
b10010 $
b10010 (
b10010 *
1%
#6440
0%
#6460
b10011 $
b10011 (
b10011 *
1%
#6480
0%
#6500
b1000 "
b1000 )
b1000 +
b0 $
b0 (
b0 *
1%
#6520
0%
#6540
b1 $
b1 (
b1 *
1%
#6560
0%
#6580
b10 $
b10 (
b10 *
1%
#6600
0%
#6620
b11 $
b11 (
b11 *
1%
#6640
0%
#6660
b100 $
b100 (
b100 *
1%
#6680
0%
#6700
b101 $
b101 (
b101 *
1%
#6720
0%
#6740
b110 $
b110 (
b110 *
1%
#6760
0%
#6780
b111 $
b111 (
b111 *
1%
#6800
0%
#6820
b1000 $
b1000 (
b1000 *
1%
#6840
0%
#6860
b1001 $
b1001 (
b1001 *
1%
#6880
0%
#6900
b1010 $
b1010 (
b1010 *
1%
#6920
0%
#6940
0#
0-
b1011 $
b1011 (
b1011 *
1%
#6960
0%
#6980
b1100 $
b1100 (
b1100 *
1%
#7000
0%
#7020
b1101 $
b1101 (
b1101 *
1%
#7040
0%
#7060
b1110 $
b1110 (
b1110 *
1%
#7080
0%
#7100
b1111 $
b1111 (
b1111 *
1%
#7120
0%
#7140
b10000 $
b10000 (
b10000 *
1%
#7160
0%
#7180
1#
1-
b10001 $
b10001 (
b10001 *
1%
#7200
0%
#7220
b10010 $
b10010 (
b10010 *
1%
#7240
0%
#7260
b10011 $
b10011 (
b10011 *
1%
#7280
0%
#7300
b1001 "
b1001 )
b1001 +
b0 $
b0 (
b0 *
1%
#7320
0%
#7340
b1 $
b1 (
b1 *
1%
#7360
0%
#7380
b10 $
b10 (
b10 *
1%
#7400
0%
#7420
b11 $
b11 (
b11 *
1%
#7440
0%
#7460
b100 $
b100 (
b100 *
1%
#7480
0%
#7500
b101 $
b101 (
b101 *
1%
#7520
0%
#7540
b110 $
b110 (
b110 *
1%
#7560
0%
#7580
b111 $
b111 (
b111 *
1%
#7600
0%
#7620
b1000 $
b1000 (
b1000 *
1%
#7640
0%
#7660
b1001 $
b1001 (
b1001 *
1%
#7680
0%
#7700
b1010 $
b1010 (
b1010 *
1%
#7720
0%
#7740
0#
0-
b1011 $
b1011 (
b1011 *
1%
#7760
0%
#7780
b1100 $
b1100 (
b1100 *
1%
#7800
0%
#7820
b1101 $
b1101 (
b1101 *
1%
#7840
0%
#7860
b1110 $
b1110 (
b1110 *
1%
#7880
0%
#7900
b1111 $
b1111 (
b1111 *
1%
#7920
0%
#7940
b10000 $
b10000 (
b10000 *
1%
#7960
0%
#7980
1#
1-
b10001 $
b10001 (
b10001 *
1%
#8000
0%
#8020
b10010 $
b10010 (
b10010 *
1%
#8040
0%
#8060
b10011 $
b10011 (
b10011 *
1%
#8080
0%
#8100
b1010 "
b1010 )
b1010 +
b0 $
b0 (
b0 *
1%
#8120
0%
#8140
0!
0.
b1 $
b1 (
b1 *
1%
#8160
0%
#8180
b10 $
b10 (
b10 *
1%
#8200
0%
#8220
b11 $
b11 (
b11 *
1%
#8240
0%
#8260
b100 $
b100 (
b100 *
1%
#8280
0%
#8300
b101 $
b101 (
b101 *
1%
#8320
0%
#8340
b110 $
b110 (
b110 *
1%
#8360
0%
#8380
b111 $
b111 (
b111 *
1%
#8400
0%
#8420
b1000 $
b1000 (
b1000 *
1%
#8440
0%
#8460
b1001 $
b1001 (
b1001 *
1%
#8480
0%
#8500
b1010 $
b1010 (
b1010 *
1%
#8520
0%
#8540
0#
0-
b1011 $
b1011 (
b1011 *
1%
#8560
0%
#8580
b1100 $
b1100 (
b1100 *
1%
#8600
0%
#8620
b1101 $
b1101 (
b1101 *
1%
#8640
0%
#8660
b1110 $
b1110 (
b1110 *
1%
#8680
0%
#8700
b1111 $
b1111 (
b1111 *
1%
#8720
0%
#8740
b10000 $
b10000 (
b10000 *
1%
#8760
0%
#8780
1#
1-
b10001 $
b10001 (
b10001 *
1%
#8800
0%
#8820
b10010 $
b10010 (
b10010 *
1%
#8840
0%
#8860
b10011 $
b10011 (
b10011 *
1%
#8880
0%
#8900
b1011 "
b1011 )
b1011 +
b0 $
b0 (
b0 *
1%
#8920
0%
#8940
b1 $
b1 (
b1 *
1%
#8960
0%
#8980
b10 $
b10 (
b10 *
1%
#9000
0%
#9020
b11 $
b11 (
b11 *
1%
#9040
0%
#9060
b100 $
b100 (
b100 *
1%
#9080
0%
#9100
b101 $
b101 (
b101 *
1%
#9120
0%
#9140
b110 $
b110 (
b110 *
1%
#9160
0%
#9180
b111 $
b111 (
b111 *
1%
#9200
0%
#9220
b1000 $
b1000 (
b1000 *
1%
#9240
0%
#9260
b1001 $
b1001 (
b1001 *
1%
#9280
0%
#9300
b1010 $
b1010 (
b1010 *
1%
#9320
0%
#9340
0#
0-
b1011 $
b1011 (
b1011 *
1%
#9360
0%
#9380
b1100 $
b1100 (
b1100 *
1%
#9400
0%
#9420
b1101 $
b1101 (
b1101 *
1%
#9440
0%
#9460
b1110 $
b1110 (
b1110 *
1%
#9480
0%
#9500
b1111 $
b1111 (
b1111 *
1%
#9520
0%
#9540
b10000 $
b10000 (
b10000 *
1%
#9560
0%
#9580
1#
1-
b10001 $
b10001 (
b10001 *
1%
#9600
0%
#9620
b10010 $
b10010 (
b10010 *
1%
#9640
0%
#9660
b10011 $
b10011 (
b10011 *
1%
#9680
0%
#9700
b1100 "
b1100 )
b1100 +
b0 $
b0 (
b0 *
1%
#9720
0%
#9740
1!
1.
b1 $
b1 (
b1 *
1%
#9760
0%
#9780
b10 $
b10 (
b10 *
1%
#9800
0%
#9820
b11 $
b11 (
b11 *
1%
#9840
0%
#9860
b100 $
b100 (
b100 *
1%
#9880
0%
#9900
b101 $
b101 (
b101 *
1%
#9920
0%
#9940
b110 $
b110 (
b110 *
1%
#9960
0%
#9980
b111 $
b111 (
b111 *
1%
#10000
0%
#10020
b1000 $
b1000 (
b1000 *
1%
#10040
0%
#10060
b1001 $
b1001 (
b1001 *
1%
#10080
0%
#10100
b1010 $
b1010 (
b1010 *
1%
#10120
0%
#10140
0#
0-
b1011 $
b1011 (
b1011 *
1%
#10160
0%
#10180
b1100 $
b1100 (
b1100 *
1%
#10200
0%
#10220
b1101 $
b1101 (
b1101 *
1%
#10240
0%
#10260
b1110 $
b1110 (
b1110 *
1%
#10280
0%
#10300
b1111 $
b1111 (
b1111 *
1%
#10320
0%
#10340
b10000 $
b10000 (
b10000 *
1%
#10360
0%
#10380
1#
1-
b10001 $
b10001 (
b10001 *
1%
#10400
0%
#10420
b10010 $
b10010 (
b10010 *
1%
#10440
0%
#10460
b10011 $
b10011 (
b10011 *
1%
#10480
0%
#10500
b1101 "
b1101 )
b1101 +
b0 $
b0 (
b0 *
1%
#10520
0%
#10540
b1 $
b1 (
b1 *
1%
#10560
0%
#10580
b10 $
b10 (
b10 *
1%
#10600
0%
#10620
b11 $
b11 (
b11 *
1%
#10640
0%
#10660
b100 $
b100 (
b100 *
1%
#10680
0%
#10700
b101 $
b101 (
b101 *
1%
#10720
0%
#10740
b110 $
b110 (
b110 *
1%
#10760
0%
#10780
b111 $
b111 (
b111 *
1%
#10800
0%
#10820
b1000 $
b1000 (
b1000 *
1%
#10840
0%
#10860
b1001 $
b1001 (
b1001 *
1%
#10880
0%
#10900
b1010 $
b1010 (
b1010 *
1%
#10920
0%
#10940
0#
0-
b1011 $
b1011 (
b1011 *
1%
#10960
0%
#10980
b1100 $
b1100 (
b1100 *
1%
#11000
0%
#11020
b1101 $
b1101 (
b1101 *
1%
#11040
0%
#11060
b1110 $
b1110 (
b1110 *
1%
#11080
0%
#11100
b1111 $
b1111 (
b1111 *
1%
#11120
0%
#11140
b10000 $
b10000 (
b10000 *
1%
#11160
0%
#11180
1#
1-
b10001 $
b10001 (
b10001 *
1%
#11200
0%
#11220
b10010 $
b10010 (
b10010 *
1%
#11240
0%
#11260
b10011 $
b10011 (
b10011 *
1%
#11280
0%
#11300
b1110 "
b1110 )
b1110 +
b0 $
b0 (
b0 *
1%
#11320
0%
#11340
b1 $
b1 (
b1 *
1%
#11360
0%
#11380
b10 $
b10 (
b10 *
1%
#11400
0%
#11420
b11 $
b11 (
b11 *
1%
#11440
0%
#11460
b100 $
b100 (
b100 *
1%
#11480
0%
#11500
b101 $
b101 (
b101 *
1%
#11520
0%
#11540
b110 $
b110 (
b110 *
1%
#11560
0%
#11580
b111 $
b111 (
b111 *
1%
#11600
0%
#11620
b1000 $
b1000 (
b1000 *
1%
#11640
0%
#11660
b1001 $
b1001 (
b1001 *
1%
#11680
0%
#11700
b1010 $
b1010 (
b1010 *
1%
#11720
0%
#11740
0#
0-
b1011 $
b1011 (
b1011 *
1%
#11760
0%
#11780
b1100 $
b1100 (
b1100 *
1%
#11800
0%
#11820
b1101 $
b1101 (
b1101 *
1%
#11840
0%
#11860
b1110 $
b1110 (
b1110 *
1%
#11880
0%
#11900
b1111 $
b1111 (
b1111 *
1%
#11920
0%
#11940
b10000 $
b10000 (
b10000 *
1%
#11960
0%
#11980
1#
1-
b10001 $
b10001 (
b10001 *
1%
#12000
0%
#12020
b10010 $
b10010 (
b10010 *
1%
#12040
0%
#12060
b10011 $
b10011 (
b10011 *
1%
#12080
0%
#12100
b0 "
b0 )
b0 +
b0 $
b0 (
b0 *
1%
#12120
0%
#12140
1&
1,
b1 $
b1 (
b1 *
1%
#12160
0%
#12180
b10 $
b10 (
b10 *
1%
#12200
0%
#12220
b11 $
b11 (
b11 *
1%
#12240
0%
#12260
b100 $
b100 (
b100 *
1%
#12280
0%
#12300
b101 $
b101 (
b101 *
1%
#12320
0%
#12340
b110 $
b110 (
b110 *
1%
#12360
0%
#12380
b111 $
b111 (
b111 *
1%
#12400
0%
#12420
0&
0,
b1000 $
b1000 (
b1000 *
1%
#12440
0%
#12460
b1001 $
b1001 (
b1001 *
1%
#12480
0%
#12500
b1010 $
b1010 (
b1010 *
1%
#12520
0%
#12540
0#
0-
b1011 $
b1011 (
b1011 *
1%
#12560
0%
#12580
b1100 $
b1100 (
b1100 *
1%
#12600
0%
#12620
b1101 $
b1101 (
b1101 *
1%
#12640
0%
#12660
b1110 $
b1110 (
b1110 *
1%
#12680
0%
#12700
b1111 $
b1111 (
b1111 *
1%
#12720
0%
#12740
b10000 $
b10000 (
b10000 *
1%
#12760
0%
#12780
1#
1-
b10001 $
b10001 (
b10001 *
1%
#12800
0%
#12820
b10010 $
b10010 (
b10010 *
1%
#12840
0%
#12860
b10011 $
b10011 (
b10011 *
1%
#12880
0%
#12900
b1 "
b1 )
b1 +
b0 $
b0 (
b0 *
1%
#12920
0%
#12940
1&
1,
b1 $
b1 (
b1 *
1%
#12960
0%
#12980
b10 $
b10 (
b10 *
1%
#13000
0%
#13020
b11 $
b11 (
b11 *
1%
#13040
0%
#13060
b100 $
b100 (
b100 *
1%
#13080
0%
#13100
b101 $
b101 (
b101 *
1%
#13120
0%
#13140
b110 $
b110 (
b110 *
1%
#13160
0%
#13180
b111 $
b111 (
b111 *
1%
#13200
0%
#13220
0&
0,
b1000 $
b1000 (
b1000 *
1%
#13240
0%
#13260
b1001 $
b1001 (
b1001 *
1%
#13280
0%
#13300
b1010 $
b1010 (
b1010 *
1%
#13320
0%
#13340
0#
0-
b1011 $
b1011 (
b1011 *
1%
#13360
0%
#13380
b1100 $
b1100 (
b1100 *
1%
#13400
0%
#13420
b1101 $
b1101 (
b1101 *
1%
#13440
0%
#13460
b1110 $
b1110 (
b1110 *
1%
#13480
0%
#13500
b1111 $
b1111 (
b1111 *
1%
#13520
0%
#13540
b10000 $
b10000 (
b10000 *
1%
#13560
0%
#13580
1#
1-
b10001 $
b10001 (
b10001 *
1%
#13600
0%
#13620
b10010 $
b10010 (
b10010 *
1%
#13640
0%
#13660
b10011 $
b10011 (
b10011 *
1%
#13680
0%
#13700
b10 "
b10 )
b10 +
b0 $
b0 (
b0 *
1%
#13720
0%
#13740
1&
1,
b1 $
b1 (
b1 *
1%
#13760
0%
#13780
b10 $
b10 (
b10 *
1%
#13800
0%
#13820
b11 $
b11 (
b11 *
1%
#13840
0%
#13860
b100 $
b100 (
b100 *
1%
#13880
0%
#13900
b101 $
b101 (
b101 *
1%
#13920
0%
#13940
b110 $
b110 (
b110 *
1%
#13960
0%
#13980
b111 $
b111 (
b111 *
1%
#14000
0%
#14020
0&
0,
b1000 $
b1000 (
b1000 *
1%
#14040
0%
#14060
b1001 $
b1001 (
b1001 *
1%
#14080
0%
#14100
b1010 $
b1010 (
b1010 *
1%
#14120
0%
#14140
0#
0-
b1011 $
b1011 (
b1011 *
1%
#14160
0%
#14180
b1100 $
b1100 (
b1100 *
1%
#14200
0%
#14220
b1101 $
b1101 (
b1101 *
1%
#14240
0%
#14260
b1110 $
b1110 (
b1110 *
1%
#14280
0%
#14300
b1111 $
b1111 (
b1111 *
1%
#14320
0%
#14340
b10000 $
b10000 (
b10000 *
1%
#14360
0%
#14380
1#
1-
b10001 $
b10001 (
b10001 *
1%
#14400
0%
#14420
b10010 $
b10010 (
b10010 *
1%
#14440
0%
#14460
b10011 $
b10011 (
b10011 *
1%
#14480
0%
#14500
b11 "
b11 )
b11 +
b0 $
b0 (
b0 *
1%
#14520
0%
#14540
1&
1,
b1 $
b1 (
b1 *
1%
#14560
0%
#14580
b10 $
b10 (
b10 *
1%
#14600
0%
#14620
b11 $
b11 (
b11 *
1%
#14640
0%
#14660
b100 $
b100 (
b100 *
1%
#14680
0%
#14700
b101 $
b101 (
b101 *
1%
#14720
0%
#14740
b110 $
b110 (
b110 *
1%
#14760
0%
#14780
b111 $
b111 (
b111 *
1%
#14800
0%
#14820
0&
0,
b1000 $
b1000 (
b1000 *
1%
#14840
0%
#14860
b1001 $
b1001 (
b1001 *
1%
#14880
0%
#14900
b1010 $
b1010 (
b1010 *
1%
#14920
0%
#14940
0#
0-
b1011 $
b1011 (
b1011 *
1%
#14960
0%
#14980
b1100 $
b1100 (
b1100 *
1%
#15000
0%
#15020
b1101 $
b1101 (
b1101 *
1%
#15040
0%
#15060
b1110 $
b1110 (
b1110 *
1%
#15080
0%
#15100
b1111 $
b1111 (
b1111 *
1%
#15120
0%
#15140
b10000 $
b10000 (
b10000 *
1%
#15160
0%
#15180
1#
1-
b10001 $
b10001 (
b10001 *
1%
#15200
0%
#15220
b10010 $
b10010 (
b10010 *
1%
#15240
0%
#15260
b10011 $
b10011 (
b10011 *
1%
#15280
0%
#15300
b100 "
b100 )
b100 +
b0 $
b0 (
b0 *
1%
#15320
0%
#15340
1&
1,
b1 $
b1 (
b1 *
1%
#15360
0%
#15380
b10 $
b10 (
b10 *
1%
#15400
0%
#15420
b11 $
b11 (
b11 *
1%
#15440
0%
#15460
b100 $
b100 (
b100 *
1%
#15480
0%
#15500
b101 $
b101 (
b101 *
1%
#15520
0%
#15540
b110 $
b110 (
b110 *
1%
#15560
0%
#15580
b111 $
b111 (
b111 *
1%
#15600
0%
#15620
0&
0,
b1000 $
b1000 (
b1000 *
1%
#15640
0%
#15660
b1001 $
b1001 (
b1001 *
1%
#15680
0%
#15700
b1010 $
b1010 (
b1010 *
1%
#15720
0%
#15740
0#
0-
b1011 $
b1011 (
b1011 *
1%
#15760
0%
#15780
b1100 $
b1100 (
b1100 *
1%
#15800
0%
#15820
b1101 $
b1101 (
b1101 *
1%
#15840
0%
#15860
b1110 $
b1110 (
b1110 *
1%
#15880
0%
#15900
b1111 $
b1111 (
b1111 *
1%
#15920
0%
#15940
b10000 $
b10000 (
b10000 *
1%
#15960
0%
#15980
1#
1-
b10001 $
b10001 (
b10001 *
1%
#16000
0%
#16020
b10010 $
b10010 (
b10010 *
1%
#16040
0%
#16060
b10011 $
b10011 (
b10011 *
1%
#16080
0%
#16100
b101 "
b101 )
b101 +
b0 $
b0 (
b0 *
1%
#16120
0%
#16140
1&
1,
b1 $
b1 (
b1 *
1%
#16160
0%
#16180
b10 $
b10 (
b10 *
1%
#16200
0%
#16220
b11 $
b11 (
b11 *
1%
#16240
0%
#16260
b100 $
b100 (
b100 *
1%
#16280
0%
